groot_main.py
api/__init__.py
api/api_wencai.py
src/__init__.py
src/base.py
src/boxoffice.py
src/figure.py
src/orchestrator.py
src/playback.py
src/utils.py
groot_quant-0.2.2.dist-info/LICENSE
groot_quant-0.2.2.dist-info/METADATA
groot_quant-0.2.2.dist-info/WHEEL
groot_quant-0.2.2.dist-info/entry_points.txt
groot_quant-0.2.2.dist-info/top_level.txt
groot_quant-0.2.2.dist-info/RECORD
