Metadata-Version: 2.1
Name: groot-quant
Version: 0.2.2
Summary: A quantitative tool that run strategy through a large model semantic filtering
Home-page: https://github.com/JaneShine/groot
Author: xiejingxian
Author-email: xiejingxian@zju.edu.cn
Classifier: Programming Language :: Python :: 3
Classifier: License :: OSI Approved :: MIT License
Classifier: Operating System :: OS Independent
Requires-Python: >=3.6
License-File: LICENSE
Requires-Dist: dash (==2.17.1)
Requires-Dist: flask (==3.0.3)
Requires-Dist: pywencai (==0.12.2)
Requires-Dist: tqdm (==4.66.2)
Requires-Dist: tushare (==1.4.7)
Requires-Dist: watchdog (==4.0.1)
Requires-Dist: pyfolio (==0.9.2)
